paps_settings/__init__.py
paps_settings/plugin.py
paps_settings/settable_plugin.py
paps_settings-0.2.6a0.dist-info/DESCRIPTION.rst
paps_settings-0.2.6a0.dist-info/METADATA
paps_settings-0.2.6a0.dist-info/RECORD
paps_settings-0.2.6a0.dist-info/WHEEL
paps_settings-0.2.6a0.dist-info/metadata.json
paps_settings-0.2.6a0.dist-info/top_level.txt
