Metadata-Version: 2.0
Name: paps-settings
Version: 0.2.6a0
Summary: Settings plugin for paps
Home-page: https://github.com/the01/paps-settings
Author: d01 <Florian Jung>
Author-email: jungflor@gmail.com
License: MIT
Keywords: paps audience participation settings plugin
Platform: UNKNOWN
Classifier: Development Status :: 2 - Pre-Alpha
Classifier: Intended Audience :: Developers
Classifier: License :: OSI Approved :: MIT License
Classifier: Natural Language :: English
Classifier: Programming Language :: Python :: 2
Classifier: Programming Language :: Python :: 2.7
Requires-Dist: autobahn (>=0.13.0,<0.14)
Requires-Dist: flotils (<0.4.0,>=0.3.1.a0)
Requires-Dist: paps (>=0.2.3a0,<0.3.0)
Requires-Dist: twisted (>=16.0,<17.0)
